{"article_id": 393, "article_url": "https://bylaws.burnaby.ca/en/permalink/bylaw26045", "article_title": "Bylaw 14751 — Housing Agreement (5860 Olive Avenue) Bylaw 2025", "source": "burnaby_bylaws", "source_label": "Burnaby Bylaws", "government_level": "Municipal", "article_published_at": null, "has_attachments": true, "pdf_urls": "[{\"url\": \"https://bylaws.burnaby.ca/media/14000/14751.pdf\", \"title\": \"Bylaw Document\"}]", "briefs": [{"id": 248, "title": "Burnaby Housing Agreement locks 47 non-market rental units at 5860 Olive Avenue", "summary": "Burnaby Council adopted Bylaw 14751 on June 24, 2025, authorizing a Housing Agreement with Polygon Onyx Homes Ltd. that legally binds 47 non-market rental units in a 34-storey tower to affordability and tenant-eligibility requirements under the Local Government Act.", "action_required": "If you own or manage rental property in this development, review the Housing Agreement's rent and tenant-eligibility obligations immediately.", "key_dates": [], "industries": "Construction & Development, Landlord & Property Mgmt", "locations": "Burnaby", "government_level": "Municipal", "article_url": "https://bylaws.burnaby.ca/en/permalink/bylaw26045", "article_title": "Bylaw 14751 — Housing Agreement (5860 Olive Avenue) Bylaw 2025", "article_published_at": null, "source": "burnaby_bylaws", "source_label": "Burnaby Bylaws", "created_at": "2026-03-20T01:50:56.462235"}]}