{"article_id": 220, "article_url": "https://www.bclaws.gov.bc.ca/civix/document/id/bcgaz2/bcgaz2/v68n22_247-2025", "article_title": "B.C. Reg. 247/2025 – OIC 600/2025", "source": "bc_gazette_part2", "source_label": "BC Gazette Part II", "government_level": "Provincial", "article_published_at": "2025-12-18T00:00:00", "has_attachments": false, "pdf_urls": null, "briefs": [{"id": 312, "title": "Insurance agents and adjusters in BC must now follow updated continuing education rules", "summary": "BC updated its Insurance Council rules to clarify which insurance professionals must complete ongoing training. General insurance agents, life insurance agents, salespersons, and insurance adjusters are covered — but restricted insurance agents and their staff are excluded.", "action_required": "Check if your insurance licence type requires continuing education under the updated Insurance Council Regulation.", "key_dates": [], "industries": "Finance & Insurance", "locations": "British Columbia", "government_level": "Provincial", "is_proposal": false, "article_url": "https://www.bclaws.gov.bc.ca/civix/document/id/bcgaz2/bcgaz2/v68n22_247-2025", "article_title": "B.C. Reg. 247/2025 – OIC 600/2025", "article_published_at": "2025-12-18T00:00:00", "source": "bc_gazette_part2", "source_label": "BC Gazette Part II", "created_at": "2026-04-23T00:24:47.017897"}]}