{"article_id": 100, "article_url": "https://www.bclaws.gov.bc.ca/civix/document/id/bcgaz2/bcgaz2/v68n18_191-2025", "article_title": "B.C. Reg. 191/2025 – OIC 501/2025", "source": "bc_gazette_part2", "source_label": "BC Gazette Part II", "government_level": "Provincial", "article_published_at": "2025-10-28T00:00:00", "has_attachments": false, "pdf_urls": null, "briefs": [{"id": 76, "title": "ICBC Rate Review Deadline Extended to 2027, December 2025 Filing Exempted", "summary": "BC has updated the rules governing how ICBC (the province's public auto insurer) sets its rates. The current policy review period has been extended by one year to March 31, 2027, and ICBC has been exempted from having to file for a general rate change order (a formal request to adjust what drivers pay for insurance) by December 15, 2025.", "action_required": null, "key_dates": [{"label": "ICBC general rate change filing exemption deadline — BC regulation", "date": "2025-11-15"}], "industries": "Finance & Insurance, Transportation & Logistics", "locations": "British Columbia", "government_level": "Provincial", "is_proposal": false, "article_url": "https://www.bclaws.gov.bc.ca/civix/document/id/bcgaz2/bcgaz2/v68n18_191-2025", "article_title": "B.C. Reg. 191/2025 – OIC 501/2025", "article_published_at": "2025-10-28T00:00:00", "source": "bc_gazette_part2", "source_label": "BC Gazette Part II", "created_at": "2026-04-23T20:23:36.206730"}]}