{"article_id": 242, "article_url": "https://www.bclaws.gov.bc.ca/civix/document/id/bcgaz2/bcgaz2/v68n20_204-2025", "article_title": "B.C. Reg. 204/2025 – OIC 529/2025", "source": "bc_gazette_part2", "source_label": "BC Gazette Part II", "government_level": "Provincial", "article_published_at": "2025-11-24T00:00:00", "has_attachments": false, "pdf_urls": null, "briefs": [{"id": 332, "title": "BC Securities Rules Updated: WKSI Shelf Prospectus Fees Now Have New Filing Deadlines", "summary": "BC updated its securities rules to add a new type of fundraising document called a WKSI base shelf prospectus (a fast-track filing used by large, well-known companies to raise money from the public) and set out specific fee-reporting deadlines for it.", "action_required": "If you file a WKSI base shelf prospectus in BC, report gross proceeds and pay fees within 5 business days after each month-end or within 30 days after each tranche closes.", "key_dates": [{"label": "BC WKSI base shelf prospectus fee rules take effect", "date": "2025-11-28"}], "industries": "Finance & Insurance, Professional Services", "locations": "British Columbia", "government_level": "Provincial", "is_proposal": false, "article_url": "https://www.bclaws.gov.bc.ca/civix/document/id/bcgaz2/bcgaz2/v68n20_204-2025", "article_title": "B.C. Reg. 204/2025 – OIC 529/2025", "article_published_at": "2025-11-24T00:00:00", "source": "bc_gazette_part2", "source_label": "BC Gazette Part II", "created_at": "2026-04-23T00:27:50.332128"}]}